ddgun/__init__.py
ddgun/aa.py
ddgun/cli.py
ddgun/ddgun.py
ddgun/funcs_3d.py
ddgun/funcs_seq.py
ddgun/profile.py
ddgun/structure.py
ddgun/utils.py
ddgun/data/aaindex1
ddgun/data/aaindex2
ddgun/data/aaindex3
ddgun/data/amino_acids.tsv
ddgun-0.0.2.dist-info/LICENSE
ddgun-0.0.2.dist-info/METADATA
ddgun-0.0.2.dist-info/WHEEL
ddgun-0.0.2.dist-info/entry_points.txt
ddgun-0.0.2.dist-info/top_level.txt
ddgun-0.0.2.dist-info/RECORD
